{
  "lastUpdated": "2026-03-31T14:30:00.000Z",
  "source": "https://www.bcb.gob.bo",
  "records": [
    {
      "timestamp": "2026-03-27T09:00:00.000Z",
      "compra": 6.86,
      "venta": 6.96
    },
    {
      "timestamp": "2026-03-28T09:00:00.000Z",
      "compra": 6.86,
      "venta": 6.96
    },
    {
      "timestamp": "2026-03-29T09:00:00.000Z",
      "compra": 6.86,
      "venta": 6.97
    },
    {
      "timestamp": "2026-03-30T09:00:00.000Z",
      "compra": 6.86,
      "venta": 6.97
    },
    {
      "timestamp": "2026-03-31T09:00:00.000Z",
      "compra": 6.86,
      "venta": 6.97
    }
  ]
}
